pyspark_delta_utility/__init__.py
pyspark_delta_utility/crud_utility.py
pyspark_delta_utility/transformation_utility.py
pyspark_delta_utility-0.2.0.dist-info/LICENSE
pyspark_delta_utility-0.2.0.dist-info/WHEEL
pyspark_delta_utility-0.2.0.dist-info/METADATA
pyspark_delta_utility-0.2.0.dist-info/RECORD
