Metadata-Version: 2.1
Name: pyspark-delta-utility
Version: 0.2.0
Summary: A useful python package that consists of pyspark and delta utilities
License: MIT
Author: Kyle Ahn
Requires-Python: >=3.9,<3.10
Classifier: License :: OSI Approved :: MIT License
Classifier: Programming Language :: Python :: 3
Classifier: Programming Language :: Python :: 3.9
